MUX_21/mux_21.sv
module mux21(a_i,b_i,sel_i,y_o);
input logic [7:0]a_i;
input logic [7:0]b_i;
input logic sel_i;

output logic [7:0]y_o;


always_comb begin

y_o=sel_i?b_i:a_i;


end

endmodule

MUX_21/mux_21_tb.sv
module mux21_tb();

logic [7:0]a_i;
logic [7:0]b_i;
logic sel_i;

logic [7:0]y_o;

mux21 dut(a_i,b_i,sel_i,y_o);

initial begin
	$dumpfile("day1.vcd");
	$dumpvars(0,mux21_tb);
	for(int i=0;i<10;i++) begin
	a_i=$urandom_range(0,8'hFF);
	b_i=$urandom_range(0,8'hFF);
	sel_i=$random%2;
	#5;
	end

end





endmodule

MUX_21/day1.vcd
$date
	Sun Jun 30 23:18:01 2024
$end
$version
	Icarus Verilog
$end
$timescale
	1s
$end
$scope module mux21_tb $end
$var wire 8 ! y_o [7:0] $end
$var reg 8 " a_i [7:0] $end
$var reg 8 # b_i [7:0] $end
$var reg 1 $ sel_i $end
$scope module dut $end
$var wire 8 % a_i [7:0] $end
$var wire 8 & b_i [7:0] $end
$var wire 1 $ sel_i $end
$var reg 8 ' y_o [7:0] $end
$upscope $end
$scope begin $ivl_for_loop0 $end
$var integer 32 ( i [31:0] $end
$upscope $end
$upscope $end
$enddefinitions $end
#0
$dumpvars
b0 (
b10010010 '
b1000000 &
b10010010 %
0$
b1000000 #
b10010010 "
b10010010 !
$end
#5
b110001 !
b110001 '
1$
b110001 #
b110001 &
b100 "
b100 %
b1 (
#10
b11000110 !
b11000110 '
b11000110 #
b11000110 &
b10000110 "
b10000110 %
b10 (
#15
b1001 !
b1001 '
b1001 #
b1001 &
b110010 "
b110010 %
b11 (
#20
b10000110 !
b10000110 '
b10000110 #
b10000110 &
b10000000 "
b10000000 %
b100 (
#25
b10011110 !
b10011110 '
b10011110 #
b10011110 &
b10111011 "
b10111011 %
b101 (
#30
b11000110 !
b11000110 '
b11000110 #
b11000110 &
b11110110 "
b11110110 %
b110 (
#35
b11111100 !
b11111100 '
0$
b1100011 #
b1100011 &
b11111100 "
b11111100 %
b111 (
#40
b1010101 !
b1010101 '
1$
b1010101 #
b1010101 &
b1100010 "
b1100010 %
b1000 (
#45
b111011 !
b111011 '
b111011 #
b111011 &
b11110010 "
b11110010 %
b1001 (
#50
b1010 (
