edge_detector/edge.sv
/* description of what design does
Scenario:

    The input signal d starts as low (0).
    It transitions to high (1) between clock pulses.

Timesteps:

    Before Clock Pulse:
        d: 0
        a_ff (previous value): 0 (from prior clock cycle)
        Outputs: rising_edge_o, falling_edge_o: Both low (0)

    Clock Pulse Arrival:
        clk goes high (positive edge).
        a_ff captures the current d value, which is now high (1) due to the recent transition.

    Edge Detection:
        Combinational logic instantly sees d as high (1) and a_ff (previous) as low (0).
        This satisfies the rising edge condition (~a_ff & d).
        rising_edge_o goes high (1) for this one clock cycle only.

    After Clock Pulse:
        clk goes low (negative edge).
        rising_edge_o goes back to low (0) as the edge has been detected.
        a_ff keeps the current d value (high - 1).

In short:

    Clock captures the input value.
    Combinational logic instantly checks for edges based on current and previous values.
    Edge detection outputs signal the event for one clock cycle.

*/





module edge_detect(clk,reset,d,rising_edge_o,falling_edge_o);
input logic clk,reset;
input logic d;

output logic rising_edge_o;
output logic falling_edge_o;

logic a_ff;

always_ff@(posedge clk or posedge reset) begin
	if (reset)
	a_ff<=1'b0;
	else
	a_ff<=d;
end

// when a_ff=0 and d=1 
assign rising_edge_o=~a_ff & d;
// when a_ff=1 and d=0 
assign falling_edge_o=a_ff & ~d;


endmodule

edge_detector/edge_tb.sv


module edge_tb();

logic clk,reset;
logic d;
logic rising_edge_o;
logic falling_edge_o;

edge_detect dut(clk,reset,d,rising_edge_o,falling_edge_o);

//clk signal
always begin
	clk=1'b0;
	#10;
	clk=1'b1;
	#10;
end

initial begin
	$dumpfile("edge.vcd");
	$dumpvars(0,edge_tb);

//here @(posedge clk) delays the next line by one clock cyle 



	// initialising 
	reset=1'b1;
	d=1'b0;
	//disabling reset
	@(posedge clk);
	reset<=1'b0;
	//changing d	
	@(posedge clk);

	// in an iteration d is assigned a random value for an interval of one
	// clk cycle this is done by using $random and  @(posedge clk) which
	// delays the next iteration by 1 clk cycle
	for(int i=0;i<32;i++) begin
	// $random gives a 32 bit value but modulo with 2 leads to a remainder
	// of either 0 or 1
	d<=$random%2;
	@(posedge clk);
	end
	$finish;
end



endmodule

edge_detector/edge.vcd
$date
	Thu Jul  4 22:51:27 2024
$end
$version
	Icarus Verilog
$end
$timescale
	1s
$end
$scope module edge_tb $end
$var wire 1 ! rising_edge_o $end
$var wire 1 " falling_edge_o $end
$var reg 1 # clk $end
$var reg 1 $ d $end
$var reg 1 % reset $end
$scope module dut $end
$var wire 1 # clk $end
$var wire 1 $ d $end
$var wire 1 " falling_edge_o $end
$var wire 1 % reset $end
$var wire 1 ! rising_edge_o $end
$var reg 1 & a_ff $end
$upscope $end
$scope begin $ivl_for_loop0 $end
$var integer 32 ' i [31:0] $end
$upscope $end
$upscope $end
$enddefinitions $end
#0
$dumpvars
b0 '
0&
1%
0$
0#
0"
0!
$end
#10
0%
1#
#20
0#
#30
1#
#40
0#
#50
1!
1$
b1 '
1#
#60
0#
#70
0!
1&
b10 '
1#
#80
0#
#90
b11 '
1#
#100
0#
#110
b100 '
1#
#120
0#
#130
b101 '
1#
#140
0#
#150
b110 '
1#
#160
0#
#170
1"
0$
b111 '
1#
#180
0#
#190
1!
0"
0&
1$
b1000 '
1#
#200
0#
#210
0!
1&
b1001 '
1#
#220
0#
#230
1"
0$
b1010 '
1#
#240
0#
#250
1!
0"
0&
1$
b1011 '
1#
#260
0#
#270
0!
1&
b1100 '
1#
#280
0#
#290
1"
0$
b1101 '
1#
#300
0#
#310
1!
0"
0&
1$
b1110 '
1#
#320
0#
#330
1"
0!
1&
0$
b1111 '
1#
#340
0#
#350
1!
0"
0&
1$
b10000 '
1#
#360
0#
#370
1"
0!
1&
0$
b10001 '
1#
#380
0#
#390
1!
0"
0&
1$
b10010 '
1#
#400
0#
#410
0!
1&
b10011 '
1#
#420
0#
#430
1"
0$
b10100 '
1#
#440
0#
#450
1!
0"
0&
1$
b10101 '
1#
#460
0#
#470
1"
0!
1&
0$
b10110 '
1#
#480
0#
#490
0"
0&
b10111 '
1#
#500
0#
#510
b11000 '
1#
#520
0#
#530
1!
1$
b11001 '
1#
#540
0#
#550
1"
0!
1&
0$
b11010 '
1#
#560
0#
#570
1!
0"
0&
1$
b11011 '
1#
#580
0#
#590
0!
1&
b11100 '
1#
#600
0#
#610
b11101 '
1#
#620
0#
#630
b11110 '
1#
#640
0#
#650
1"
0$
b11111 '
1#
#660
0#
#670
0"
0&
b100000 '
1#
