ALU/alu.sv
module alu(a_i,b_i,op_i,alu_o);
input     logic [7:0]   a_i;  //First 8-bit input vector
input     logic [7:0]   b_i;  //Second 8-bit input vector
input     logic [2:0]   op_i; //Encoded operation

output    logic [7:0]   alu_o; //ALU output

  localparam  OP_ADD = 3'b000;
  localparam  OP_SUB = 3'b001;
  localparam  OP_SLL = 3'b010;
  localparam  OP_LSR = 3'b011;
  localparam  OP_AND = 3'b100;
  localparam  OP_OR  = 3'b101;
  localparam  OP_XOR = 3'b110;
  localparam  OP_EQL = 3'b111;

  logic carry;

always_comb begin
	case(op_i)
		//add
		OP_ADD: begin
			{carry,alu_o}={1'b0,a_i}+{1'b0,b_i};

		end
		//sub
		OP_SUB: begin
			alu_o=a_i-b_i;
		end
		//sll
		OP_SLL: begin
			alu_o[7:0]=a_i<<b_i[2:0];
		end
		//lsr
		OP_LSR: begin
			alu_o[7:0]=a_i>>b_i[2:0];
		end

		//and
		OP_AND: begin
			alu_o=a_i&b_i;
		end
		//or
		OP_OR: begin
			alu_o=a_i | b_i;
		end
		//xor
		OP_XOR: begin
			alu_o=a_i^b_i;
		end

		//eql
		OP_EQL: begin
			if(a_i==b_i)
			alu_o=8'b1;
			else
			alu_o=8'b0;
		end
	

	endcase	

end

endmodule

ALU/alu_tb.sv
module alu_tb();
logic [7:0]   a_i;  //First 8-bit input vector
logic [7:0]   b_i;  //Second 8-bit input vector
logic [2:0]   op_i; //Encoded operation

logic [7:0]   alu_o; //ALU output

alu dut (a_i,b_i,op_i,alu_o);

initial begin
	$dumpfile("alu.vcd");
	$dumpvars(0,alu_tb);

	for(int i=0;i<=7;i++) begin
		for(int j=0;j<7;j++) begin
			
			a_i=$urandom_range(0,8'hFF);
			b_i=$urandom_range(0,8'hFF);
			op_i=3'(i);
			#5;

		end
	end

end
endmodule

ALU/alu.vcd
$date
	Sun Jul  7 11:03:40 2024
$end
$version
	Icarus Verilog
$end
$timescale
	1s
$end
$scope module alu_tb $end
$var wire 8 ! alu_o [7:0] $end
$var reg 8 " a_i [7:0] $end
$var reg 8 # b_i [7:0] $end
$var reg 3 $ op_i [2:0] $end
$scope module dut $end
$var wire 8 % a_i [7:0] $end
$var wire 8 & b_i [7:0] $end
$var wire 3 ' op_i [2:0] $end
$var reg 8 ( alu_o [7:0] $end
$var reg 1 ) carry $end
$upscope $end
$scope begin $ivl_for_loop0 $end
$var integer 32 * i [31:0] $end
$scope begin $ivl_for_loop1 $end
$var integer 32 + j [31:0] $end
$upscope $end
$upscope $end
$upscope $end
$enddefinitions $end
#0
$dumpvars
b0 +
b0 *
0)
b11010010 (
b0 '
b1000000 &
b10010010 %
b0 $
b1000000 #
b10010010 "
b11010010 !
$end
#5
b110101 !
b110101 (
b110001 #
b110001 &
b100 "
b100 %
b1 +
#10
1)
b1001100 !
b1001100 (
b11000110 #
b11000110 &
b10000110 "
b10000110 %
b10 +
#15
0)
b111011 !
b111011 (
b1001 #
b1001 &
b110010 "
b110010 %
b11 +
#20
1)
b110 !
b110 (
b10000110 #
b10000110 &
b10000000 "
b10000000 %
b100 +
#25
b1011001 !
b1011001 (
b10011110 #
b10011110 &
b10111011 "
b10111011 %
b101 +
#30
b10111100 !
b10111100 (
b11000110 #
b11000110 &
b11110110 "
b11110110 %
b110 +
#35
b10011001 !
b10011001 (
b1 $
b1 '
b1100011 #
b1100011 &
b11111100 "
b11111100 %
b1 *
b0 +
#40
b1101 !
b1101 (
b1010101 #
b1010101 &
b1100010 "
b1100010 %
b1 +
#45
b10110111 !
b10110111 (
b111011 #
b111011 &
b11110010 "
b11110010 %
b10 +
#50
b1000010 !
b1000010 (
b11000111 #
b11000111 &
b1001 "
b1001 %
b11 +
#55
b10010010 !
b10010010 (
b1100111 #
b1100111 &
b11111001 "
b11111001 %
b100 +
#60
b10010 !
b10010 (
b1100010 #
b1100010 &
b1110100 "
b1110100 %
b101 +
#65
b1010000 !
b1010000 (
b1011110 #
b1011110 &
b10101110 "
b10101110 %
b110 +
#70
b1011000 !
b1011000 (
b10 $
b10 '
b110010 #
b110010 &
b10110 "
b10110 %
b10 *
b0 +
#75
b100000 !
b100000 (
b10000101 #
b10000101 &
b110001 "
b110001 %
b1 +
#80
b1000000 !
b1000000 (
b10010000 #
b10010000 &
b1000000 "
b1000000 %
b10 +
#85
b1001110 #
b1001110 &
b11010101 "
b11010101 %
b11 +
#90
b10010110 !
b10010110 (
b1001 #
b1001 &
b1001011 "
b1001011 %
b100 +
#95
b1100 !
b1100 (
b101001 #
b101001 &
b110 "
b110 %
b101 +
#100
b11010100 !
b11010100 (
b1101010 #
b1101010 &
b10110101 "
b10110101 %
b110 +
#105
b0 !
b0 (
b11 $
b11 '
b1010111 #
b1010111 &
b1 "
b1 %
b11 *
b0 +
#110
b1 !
b1 (
b1100111 #
b1100111 &
b10001110 "
b10001110 %
b1 +
#115
b100 !
b100 (
b10000101 #
b10000101 &
b10010001 "
b10010001 %
b10 +
#120
b1 !
b1 (
b11110 #
b11110 &
b1100101 "
b1100101 %
b11 +
#125
b111 !
b111 (
b11000101 #
b11000101 &
b11111001 "
b11111001 %
b100 +
#130
b1010 !
b1010 (
b1101100 #
b1101100 &
b10100000 "
b10100000 %
b101 +
#135
b1011 !
b1011 (
b1000100 #
b1000100 &
b10111100 "
b10111100 %
b110 +
#140
b11010001 !
b11010001 (
b100 $
b100 '
b11011011 #
b11011011 &
b11110101 "
b11110101 %
b100 *
b0 +
#145
b11000011 !
b11000011 (
b11010111 #
b11010111 &
b11100011 "
b11100011 %
b1 +
#150
b10100 !
b10100 (
b10010101 #
b10010101 &
b1011110 "
b1011110 %
b10 +
#155
b0 !
b0 (
b111000 #
b111000 &
b101 "
b101 %
b11 +
#160
b10000010 !
b10000010 (
b10100111 #
b10100111 &
b11000010 "
b11000010 %
b100 +
#165
b11101 !
b11101 (
b10011101 #
b10011101 &
b11101 "
b11101 %
b101 +
#170
b1010 !
b1010 (
b10001010 #
b10001010 &
b111111 "
b111111 %
b110 +
#175
b11111100 !
b11111100 (
b101 $
b101 '
b11101100 #
b11101100 &
b11111000 "
b11111000 %
b101 *
b0 +
#180
b10110111 !
b10110111 (
b10100110 #
b10100110 &
b10110001 "
b10110001 %
b1 +
#185
b11001111 !
b11001111 (
b11000111 #
b11000111 &
b11001111 "
b11001111 %
b10 +
#190
b11111111 !
b11111111 (
b1011011 #
b1011011 &
b11111100 "
b11111100 %
b11 +
#195
b1101111 !
b1101111 (
b101110 #
b101110 &
b1001111 "
b1001111 %
b100 +
#200
b11101101 !
b11101101 (
b11000100 #
b11000100 &
b101101 "
b101101 %
b101 +
#205
b1101100 !
b1101100 (
b1101000 #
b1101000 &
b100100 "
b100100 %
b110 +
#210
b1000011 !
b1000011 (
b110 $
b110 '
b101000 #
b101000 &
b1101011 "
b1101011 %
b110 *
b0 +
#215
b1001101 !
b1001101 (
b10000110 #
b10000110 &
b11001011 "
b11001011 %
b1 +
#220
b10000101 !
b10000101 (
b11100100 #
b11100100 &
b1100001 "
b1100001 %
b10 +
#225
b10100101 !
b10100101 (
b10011110 #
b10011110 &
b111011 "
b111011 %
b11 +
#230
b10110110 !
b10110110 (
b111111 #
b111111 &
b10001001 "
b10001001 %
b100 +
#235
b101010 !
b101010 (
b10011100 #
b10011100 &
b10110110 "
b10110110 %
b101 +
#240
b11100110 !
b11100110 (
b1101001 #
b1101001 &
b10001111 "
b10001111 %
b110 +
#245
b0 !
b0 (
b111 $
b111 '
b111100 #
b111100 &
b11000010 "
b11000010 %
b111 *
b0 +
#250
b10100100 #
b10100100 &
b10101101 "
b10101101 %
b1 +
#255
b10010101 #
b10010101 &
b11111 "
b11111 %
b10 +
#260
b1000011 #
b1000011 &
b10101100 "
b10101100 %
b11 +
#265
b1001110 #
b1001110 &
b1000111 "
b1000111 %
b100 +
#270
b10011 #
b10011 &
b11111101 "
b11111101 %
b101 +
#275
b1010001 #
b1010001 &
b10111001 "
b10111001 %
b110 +
#280
b1000 *
b111 +
